[
  {
    "id": 1,
    "title": "Fone de Ouvido Bluetooth JBL Tune 510BT",
    "store": "Amazon",
    "category": "Eletronicos",
    "oldPrice": 209.9,
    "currentPrice": 139.9,
    "discount": 33,
    "image": "https://images.unsplash.com/photo-1505740420928-5e560c06d30e?auto=format&fit=crop&w=600&q=80",
    "affiliateUrl": "https://www.amazon.com.br/?tag=SEU-CODIGO-AQUI"
  },
  {
    "id": 2,
    "title": "Smartphone Xiaomi Redmi Note 13 128GB",
    "store": "Magalu",
    "category": "Celulares",
    "oldPrice": 1199,
    "currentPrice": 899,
    "discount": 25,
    "image": "https://images.unsplash.com/photo-1598327105666-5b89351aff97?auto=format&fit=crop&w=600&q=80",
    "affiliateUrl": "https://www.magazineluiza.com.br/"
  },
  {
    "id": 3,
    "title": "Fritadeira Air Fryer Philco 4L",
    "store": "Shopee",
    "category": "Casa e Cozinha",
    "oldPrice": 399.9,
    "currentPrice": 239.9,
    "discount": 40,
    "image": "https://images.unsplash.com/photo-1585515320310-259814833e62?auto=format&fit=crop&w=600&q=80",
    "affiliateUrl": "https://shopee.com.br/?af_siteid=SEU-CODIGO-AQUI"
  },
  {
    "id": 4,
    "title": "Smartwatch Xiaomi Mi Band 8",
    "store": "Amazon",
    "category": "Eletronicos",
    "oldPrice": 329.9,
    "currentPrice": 229,
    "discount": 30,
    "image": "https://images.unsplash.com/photo-1575311373937-040b8e1fd5b6?auto=format&fit=crop&w=600&q=80",
    "affiliateUrl": "https://www.amazon.com.br/?tag=SEU-CODIGO-AQUI"
  },
  {
    "id": 5,
    "title": "Pai Rico Pai Pobre - Robert T. Kiyosaki",
    "store": "Amazon",
    "category": "Livros",
    "oldPrice": 69.9,
    "currentPrice": 49.9,
    "discount": 28,
    "image": "https://images.unsplash.com/photo-1544947950-fa07a98d237f?auto=format&fit=crop&w=600&q=80",
    "affiliateUrl": "https://www.amazon.com.br/?tag=SEU-CODIGO-AQUI"
  },
  {
    "id": 6,
    "title": "Cafeteira Nespresso Essenza Mini",
    "store": "Mercado Livre",
    "category": "Casa e Cozinha",
    "oldPrice": 459,
    "currentPrice": 299,
    "discount": 25,
    "image": "https://images.unsplash.com/photo-1517668808822-9ebb02f2a0e6?auto=format&fit=crop&w=600&q=80",
    "affiliateUrl": "https://www.mercadolivre.com.br/"
  },
  {
    "id": 101,
    "title": "Fone Bluetooth com cancelamento de ruido",
    "store": "Amazon",
    "category": "Eletronicos",
    "oldPrice": 299.9,
    "currentPrice": 179.9,
    "discount": 40,
    "image": "https://images.unsplash.com/photo-1505740420928-5e560c06d30e?auto=format&fit=crop&w=600&q=80",
    "affiliateUrl": "https://www.amazon.com.br/dp/EXEMPLO-FONE?tag=SEU-CODIGO-AQUI",
    "expiresAt": "2026-12-31T23:59:00-03:00",
    "foundAt": "2026-06-19T01:23:46.099247+00:00",
    "source": "discount_bot"
  },
  {
    "id": 102,
    "title": "Kit cozinha com organizadores",
    "store": "Shopee",
    "category": "Casa e Cozinha",
    "oldPrice": 129.9,
    "currentPrice": 74.9,
    "discount": 42,
    "image": "https://images.unsplash.com/photo-1556911220-bff31c812dba?auto=format&fit=crop&w=600&q=80",
    "affiliateUrl": "https://shopee.com.br/produto-exemplo?af_siteid=SEU-CODIGO-AQUI",
    "expiresAt": "2026-12-31T23:59:00-03:00",
    "foundAt": "2026-06-19T01:23:46.099247+00:00",
    "source": "discount_bot"
  },
  {
    "id": 103,
    "title": "Mochila executiva impermeavel",
    "store": "Mercado Livre",
    "category": "Moda",
    "oldPrice": 199.9,
    "currentPrice": 139.9,
    "discount": 30,
    "image": "https://images.unsplash.com/photo-1553062407-98eeb64c6a62?auto=format&fit=crop&w=600&q=80",
    "affiliateUrl": "https://www.mercadolivre.com.br/produto-exemplo?matt_tool=SEU-CODIGO-AQUI",
    "expiresAt": "2026-12-31T23:59:00-03:00",
    "foundAt": "2026-06-19T01:23:46.099247+00:00",
    "source": "discount_bot"
  }
]